Metadata-Version: 2.1
Name: zhengyang-env-4
Version: 0.0.2
Summary: A OpenAI Gym Env for foo
Home-page: UNKNOWN
License: UNKNOWN
Platform: UNKNOWN
Requires-Dist: gym
Requires-Dist: pybullet
